README
setup.py
git_py.egg-info/PKG-INFO
git_py.egg-info/SOURCES.txt
git_py.egg-info/dependency_links.txt
git_py.egg-info/requires.txt
git_py.egg-info/top_level.txt
gitpy/__init__.py
gitpy/branch.py
gitpy/commit.py
gitpy/config.py
gitpy/exceptions.py
gitpy/files.py
gitpy/ref.py
gitpy/ref_container.py
gitpy/remotes.py
gitpy/repository.py
gitpy/tag.py
gitpy/utils.py