Metadata-Version: 1.0
Name: git-py
Version: 1.0.1
Summary: Python bindings for the Git source control system
Home-page: UNKNOWN
Author: Rotem Yaari
Author-email: vmalloc@gmail.com
License: UNKNOWN
Platform: UNKNOWN
